{
	"version": "https://jsonfeed.org/version/1",
	"title": "benji",
	"home_page_url": "https://benji.dog",
	"feed_url": "",
	"description": "benji. not the dog.",
	"favicon": "/assets/icons/favicon-64x64.png",
	"icon": "/assets/avatar.png",
	"author": {
		"name": "benji",
		"url": "https://benji.dog",
		"avatar": "https://benji.dog/assets/avatar.png"
	},
	"items": [
		{
			"id": "https://benji.dog/watched/1685248037-fast--furious-6-2013/",
			"url": "https://benji.dog/watched/1685248037-fast--furious-6-2013/",
			"title": "Watched Fast & Furious 6, (2013) - ★★★½",
			"content_text": "",
			"date_published": "2023-05-27T00:00:00.000Z"
		},
		{
			"id": "https://benji.dog/likes/rebooting--an-indieweb-webring/",
			"url": "https://benji.dog/likes/rebooting--an-indieweb-webring/",
			"title": "Liked \"Rebooting 🕸️💍 an IndieWeb webring\"",
			"content_text": "Liked https://martymcgui.re/2023/05/20/rebooting--an-indieweb-webring/",
			"date_published": "2023-05-20T21:08:01.264+00:00"
		},
		{
			"id": "https://benji.dog/read/1684187895/",
			"url": "https://benji.dog/read/1684187895/",
			"content_text": "Read: Exit Strategy by Martha Wells",
			"date_published": "2023-05-15T00:00:00.000Z"
		},
		{
			"id": "https://benji.dog/watched/1684038336-still-a-michael-j-fox-movie-2023/",
			"url": "https://benji.dog/watched/1684038336-still-a-michael-j-fox-movie-2023/",
			"title": "Watched Still: A Michael J. Fox Movie, (2023) - ★★★★",
			"content_text": "",
			"date_published": "2023-05-13T00:00:00.000Z"
		},
		{
			"id": "https://benji.dog/read/1684009966/",
			"url": "https://benji.dog/read/1684009966/",
			"content_text": "Read: Rogue protocol by Martha Wells",
			"date_published": "2023-05-13T00:00:00.000Z"
		},
		{
			"id": "https://benji.dog/likes/one-year-of-pizza-makingdefault/",
			"url": "https://benji.dog/likes/one-year-of-pizza-makingdefault/",
			"title": "Liked \"One Year of Pizza MakingDefault\"",
			"content_text": "Liked https://rknight.me/one-year-of-pizza-making/",
			"date_published": "2023-05-07T05:01:38.838+00:00"
		},
		{
			"id": "https://benji.dog/watched/1683582482-guardians-of-the-galaxy-vol-3-2023/",
			"url": "https://benji.dog/watched/1683582482-guardians-of-the-galaxy-vol-3-2023/",
			"title": "Watched Guardians of the Galaxy Vol. 3, (2023) - ★★★★½",
			"content_text": "",
			"date_published": "2023-05-07T00:00:00.000Z"
		},
		{
			"id": "https://benji.dog/notes/1683263008/",
			"url": "https://benji.dog/notes/1683263008/",
			"content_text": "A few months ago I picked this up from a Little Free Library in the neighborhood. Today my kid picked it to read for bedtime. Happy May 4th.",
			"date_published": "2023-05-04T23:03:28.130+00:00",
			"tags": [
				"O"
			]
		},
		{
			"id": "https://benji.dog/watched/1683082297-love-antosha-2019/",
			"url": "https://benji.dog/watched/1683082297-love-antosha-2019/",
			"title": "Watched Love, Antosha, (2019) - ★★★★",
			"content_text": "",
			"date_published": "2023-05-02T00:00:00.000Z"
		},
		{
			"id": "https://benji.dog/read/1682799506/",
			"url": "https://benji.dog/read/1682799506/",
			"content_text": "Read: Artificial Condition by Martha Wells",
			"date_published": "2023-04-29T00:00:00.000Z"
		},
		{
			"id": "https://benji.dog/watched/1683082621-the-rock-1996/",
			"url": "https://benji.dog/watched/1683082621-the-rock-1996/",
			"title": "Rewatched The Rock, (1996) - ★★★½",
			"content_text": "",
			"date_published": "2023-04-28T00:00:00.000Z"
		},
		{
			"id": "https://benji.dog/likes/bad-web-dev-ideas-emoji-as-ids-in-urls/",
			"url": "https://benji.dog/likes/bad-web-dev-ideas-emoji-as-ids-in-urls/",
			"title": "Liked \"Bad web dev ideas: emoji as IDs in URLs\"",
			"content_text": "Liked https://martymcgui.re/2023/04/26/bad-web-dev-ideas-emoji-as-ids-in-urls/",
			"date_published": "2023-04-27T04:39:12.606+00:00"
		},
		{
			"id": "https://benji.dog/read/1682646685/",
			"url": "https://benji.dog/read/1682646685/",
			"content_text": "Read: Star Wars - Thrawn Trilogy - Heir to the Empire by Timothy Zahn",
			"date_published": "2023-04-27T00:00:00.000Z"
		},
		{
			"id": "https://benji.dog/watched/1683607001-ticket-to-paradise-2022/",
			"url": "https://benji.dog/watched/1683607001-ticket-to-paradise-2022/",
			"title": "Watched Ticket to Paradise, (2022) - ★★★",
			"content_text": "",
			"date_published": "2023-04-26T00:00:00.000Z"
		},
		{
			"id": "https://benji.dog/watched/1683606920-true-lies-1994/",
			"url": "https://benji.dog/watched/1683606920-true-lies-1994/",
			"title": "Rewatched True Lies, (1994) - ★★★½",
			"content_text": "",
			"date_published": "2023-04-24T00:00:00.000Z"
		},
		{
			"id": "https://benji.dog/notes/1682225824/",
			"url": "https://benji.dog/notes/1682225824/",
			"title": "Reply to https://jamesg.blog/2023/04/18/source-code-folder-names/",
			"content_text": "I've seen some people use either ~/code, ~/projects, or ~/programming. The first IDE I used was Eclipse and by default it would create projects under ~/workspace. Since then I've been using that as my source code directory but also because its a small reference to Hackers (1995).",
			"date_published": "2023-04-23T04:57:03.588+00:00"
		},
		{
			"id": "https://benji.dog/watched/1682398249-everything-everywhere-all-at-once-2022/",
			"url": "https://benji.dog/watched/1682398249-everything-everywhere-all-at-once-2022/",
			"title": "Rewatched Everything Everywhere All at Once, (2022) - ★★★★★",
			"content_text": "",
			"date_published": "2023-04-23T00:00:00.000Z"
		},
		{
			"id": "https://benji.dog/watched/1682398204-whitney-houston-i-wanna-dance-with-somebody-2022/",
			"url": "https://benji.dog/watched/1682398204-whitney-houston-i-wanna-dance-with-somebody-2022/",
			"title": "Watched Whitney Houston: I Wanna Dance with Somebody, (2022) - ★★★",
			"content_text": "",
			"date_published": "2023-04-22T00:00:00.000Z"
		},
		{
			"id": "https://benji.dog/read/1682138815/",
			"url": "https://benji.dog/read/1682138815/",
			"content_text": "Read: Pirate Cinema by Cory Doctorow",
			"date_published": "2023-04-21T00:00:00.000Z"
		},
		{
			"id": "https://benji.dog/watched/1681936062-saint-frances-2019/",
			"url": "https://benji.dog/watched/1681936062-saint-frances-2019/",
			"title": "Watched Saint Frances, (2019) - ★★★★",
			"content_text": "",
			"date_published": "2023-04-19T00:00:00.000Z"
		}
	]
}